smexplainer/__init__.py
smexplainer/_utils.py
smexplainer/_version.py
smexplainer/explain.py
smexplainer-0.0.1.dist-info/AUTHORS.rst
smexplainer-0.0.1.dist-info/LICENSE
smexplainer-0.0.1.dist-info/METADATA
smexplainer-0.0.1.dist-info/WHEEL
smexplainer-0.0.1.dist-info/top_level.txt
smexplainer-0.0.1.dist-info/RECORD
