Metadata-Version: 2.1
Name: smexplainer
Version: 0.0.1
Summary: A python library to work with molecules. Built on top of RDKit.
Home-page: UNKNOWN
Author: Emmanuel Noutahi
License: UNKNOWN
Platform: UNKNOWN
Requires-Python: >=3.7
License-File: LICENSE
License-File: AUTHORS.rst
Requires-Dist: datamol
Requires-Dist: requests-toolbelt
